[
	{
		"__TYPE__": "SharedSliceContent",
		"variation": "default",
		"primary": {
			"heading": {
				"__TYPE__": "StructuredTextContent",
				"value": [
					{
						"type": "heading1",
						"content": {
							"text": "While"
						}
					}
				]
			},
			"subheading": {
				"__TYPE__": "StructuredTextContent",
				"value": [
					{
						"type": "paragraph",
						"content": {
							"text": "Do non est sint minim."
						}
					}
				]
			},
			"body": {
				"__TYPE__": "StructuredTextContent",
				"value": [
					{
						"type": "paragraph",
						"content": {
							"text": "Officia Lorem est do esse proident. Laborum non ullamco consectetur excepteur tempor quis proident eiusmod qui amet aliqua velit."
						}
					}
				]
			},
			"button_text": {
				"__TYPE__": "FieldContent",
				"value": "near",
				"type": "Text"
			},
			"button_link": {
				"__TYPE__": "LinkContent",
				"value": {
					"__TYPE__": "ExternalLink",
					"url": "http://google.com"
				}
			},
			"cans_image": {
				"origin": {
					"id": "main",
					"url": "https://images.unsplash.com/photo-1525547719571-a2d4ac8945e2",
					"width": 3648,
					"height": 4560
				},
				"url": "https://images.unsplash.com/photo-1525547719571-a2d4ac8945e2",
				"width": 3648,
				"height": 4560,
				"edit": {
					"zoom": 1,
					"crop": {
						"x": 0,
						"y": 0
					},
					"background": "transparent"
				},
				"credits": null,
				"alt": null,
				"__TYPE__": "ImageContent",
				"thumbnails": {}
			},
			"second_heading": {
				"__TYPE__": "StructuredTextContent",
				"value": [
					{
						"type": "heading2",
						"content": {
							"text": "Division"
						}
					}
				]
			},
			"second_body": {
				"__TYPE__": "StructuredTextContent",
				"value": [
					{
						"type": "paragraph",
						"content": {
							"text": "Aliquip consectetur ullamco aute ullamco sunt dolore ipsum pariatur. Cillum qui ea id."
						}
					}
				]
			}
		},
		"items": []
	}
]